{
    "id": "https://sigel.staatsbibliothek-berlin.de/api/org/DE-1488.jsonld",
    "data": {
        "001A": [
            [
                [
                    "9006:07-12-07"
                ]
            ]
        ],
        "001B": [
            [
                [
                    "9006:18-06-18"
                ],
                {
                    "t": "11:07:35.000"
                }
            ]
        ],
        "001D": [
            [
                [
                    "9006:07-12-07"
                ]
            ]
        ],
        "001U": [
            [
                [
                    "utf8"
                ]
            ]
        ],
        "002@": [
            [
                [
                    "Tw"
                ]
            ]
        ],
        "003@": [
            [
                [
                    "986741876"
                ]
            ]
        ],
        "008H": [
            [
                {
                    "b": "HE029"
                },
                {
                    "d": "1488"
                },
                {
                    "e": "DE-1488"
                }
            ]
        ],
        "009Q": [
            [
                {
                    "u": "https://www.badkissingen.de/de/stadt/bildung-und-soziales/bildungseinrichtungen/stadtbuecherei-und-vhs/index.html"
                },
                {
                    "z": "A"
                }
            ],
            [
                {
                    "u": "http://www.bibliofranken.de/"
                },
                {
                    "z": "B"
                }
            ]
        ],
        "029@": [
            [
                {
                    "a": "Bad Kissingen StB"
                },
                {
                    "4": "c"
                }
            ]
        ],
        "029A": [
            [
                {
                    "a": "Stadtb\u00fccherei Bad Kissingen"
                }
            ]
        ],
        "032P": [
            [
                {
                    "a": "Rathausplatz 5"
                },
                {
                    "b": "Bad Kissingen"
                },
                {
                    "d": "DE"
                },
                {
                    "e": "97688"
                },
                {
                    "f": "Bayern"
                },
                {
                    "i": "Di 14.00-18-00, Mi 10.00-13.00 und 14.00-18.00, Do 14.00-19.00, Fr 12.00-17.00, Sa 10.00-13.00"
                },
                {
                    "k": "10.07591"
                },
                {
                    "l": "50.20068"
                },
                {
                    "n": "09672114"
                },
                {
                    "p": "j"
                },
                {
                    "2": "S"
                }
            ]
        ],
        "035B": [
            [
                {
                    "a": "S"
                },
                {
                    "c": "j"
                },
                {
                    "d": "49"
                },
                {
                    "e": "971"
                },
                {
                    "f": "8 07-1221"
                },
                {
                    "g": "49"
                },
                {
                    "h": "971"
                },
                {
                    "i": "8 07-1229"
                },
                {
                    "k": "stadtbuecherei@stadt.badkissingen.de"
                }
            ]
        ],
        "035E": [
            [
                {
                    "a": "H"
                },
                {
                    "b": "s"
                },
                {
                    "f": "33"
                },
                {
                    "g": "04"
                },
                {
                    "h": "06"
                }
            ]
        ],
        "035I": [
            [
                {
                    "a": "BAY"
                },
                {
                    "c": "BVB"
                },
                {
                    "e": "n"
                },
                {
                    "g": "R"
                }
            ]
        ],
        "035L": [
            [
                {
                    "a": "e"
                },
                {
                    "d": "stadtbuecherei@stadt.badkissingen.de"
                }
            ]
        ]
    },
    "_id": "DE-1488",
    "seeAlso": "https://ld.zdb-services.de/resource/organisations/DE-1488",
    "sameAs": "https://ld.zdb-services.de/resource/organisations/DE-1488",
    "identifier": "DE-1488",
    "name": "Stadtb\u00fccherei Bad Kissingen",
    "location": "Bad Kissingen",
    "type": [
        "Organization",
        "Library"
    ],
    "addressRegion": "BAY"
}