{
    "id": "https://sigel.staatsbibliothek-berlin.de/api/org/DE-2396.jsonld",
    "data": {
        "001A": [
            [
                [
                    "9006:11-05-16"
                ]
            ]
        ],
        "001B": [
            [
                [
                    "9006:17-08-20"
                ],
                {
                    "t": "10:26:45.000"
                }
            ]
        ],
        "001D": [
            [
                [
                    "9006:11-05-16"
                ]
            ]
        ],
        "001U": [
            [
                [
                    "utf8"
                ]
            ]
        ],
        "002@": [
            [
                [
                    "Tw"
                ]
            ]
        ],
        "003@": [
            [
                [
                    "1100092722"
                ]
            ]
        ],
        "008H": [
            [
                {
                    "d": "2396"
                },
                {
                    "e": "DE-2396"
                }
            ]
        ],
        "009Q": [
            [
                {
                    "u": "http://www.deutschefotothek.de/"
                },
                {
                    "z": "A"
                }
            ]
        ],
        "029@": [
            [
                {
                    "a": "Dresden Deutsche Fotothek"
                },
                {
                    "4": "c"
                }
            ]
        ],
        "029A": [
            [
                {
                    "a": "Deutsche Fotothek"
                }
            ]
        ],
        "029R": [
            [
                {
                    "9": "009030077"
                },
                {
                    "7": "Tw"
                },
                {
                    "a": "S\u00e4chsische Landesbibliothek - Staats- und Universit\u00e4tsbibliothek Dresden"
                },
                {
                    "e": "DE-14"
                }
            ]
        ],
        "032P": [
            [
                {
                    "a": "Zellescher Weg 18"
                },
                {
                    "b": "Dresden"
                },
                {
                    "d": "DE"
                },
                {
                    "e": "01069"
                },
                {
                    "f": "Sachsen"
                },
                {
                    "i": "Mo-Mi und Fr 10.00-17.00, Do 10.00-19.00"
                },
                {
                    "k": "13.73674"
                },
                {
                    "l": "51.02781"
                },
                {
                    "n": "14612000"
                },
                {
                    "p": "j"
                },
                {
                    "2": "S"
                }
            ]
        ],
        "035B": [
            [
                {
                    "a": "S"
                },
                {
                    "c": "j"
                },
                {
                    "d": "49"
                },
                {
                    "e": "351"
                },
                {
                    "f": "4 67 76 01"
                },
                {
                    "g": "49"
                },
                {
                    "h": "351"
                },
                {
                    "i": "4 67 77 33"
                },
                {
                    "k": "Deutsche.Fotothek@slub-dresden.de"
                }
            ]
        ],
        "035E": [
            [
                {
                    "a": "H"
                },
                {
                    "b": "s"
                },
                {
                    "f": "34"
                },
                {
                    "g": "02"
                },
                {
                    "h": "10"
                },
                {
                    "i": "P"
                },
                {
                    "l": "CC0"
                }
            ]
        ],
        "035G": [
            [
                {
                    "a": "Fotografiegeschichte"
                },
                {
                    "a": "Kunst"
                },
                {
                    "a": "Architektur"
                },
                {
                    "a": "Technikgeschichte"
                }
            ]
        ],
        "047A": [
            [
                {
                    "a": "Mit \u00fcber 4 Millionen Bilddokumenten ist die Deutsche Fotothek in der SLUB Dresden ein Universalarchiv der Fotografie-, Kunst- und Technikgeschichte. In unserer Bilddatenbank sind rund 1,7 Mio. Aufnahmen aus unseren Sammlungen sowie aus den Sammlungen unserer Partnerinstitutionen online und frei zug\u00e4nglich recherchierbar, mit umfassenden Service f\u00fcr wissenschaftliche und redaktionelle Nutzung."
                }
            ]
        ]
    },
    "_id": "DE-2396",
    "seeAlso": "https://ld.zdb-services.de/resource/organisations/DE-2396",
    "sameAs": "https://ld.zdb-services.de/resource/organisations/DE-2396",
    "identifier": "DE-2396",
    "name": "Deutsche Fotothek",
    "location": "Dresden",
    "type": [
        "Organization",
        "Library"
    ]
}