{
    "id": "https://sigel.staatsbibliothek-berlin.de/api/org/DE-2218.jsonld",
    "data": {
        "001A": [
            [
                [
                    "9006:09-09-14"
                ]
            ]
        ],
        "001B": [
            [
                [
                    "9006:09-11-20"
                ],
                {
                    "t": "13:24:42.000"
                }
            ]
        ],
        "001D": [
            [
                [
                    "9006:09-09-14"
                ]
            ]
        ],
        "001U": [
            [
                [
                    "utf8"
                ]
            ]
        ],
        "002@": [
            [
                [
                    "Tw"
                ]
            ]
        ],
        "003@": [
            [
                [
                    "1058117238"
                ]
            ]
        ],
        "008H": [
            [
                {
                    "d": "2218"
                },
                {
                    "e": "DE-2218"
                }
            ]
        ],
        "009Q": [
            [
                {
                    "u": "http://www.schubi-saeer.de"
                },
                {
                    "z": "A"
                }
            ]
        ],
        "029@": [
            [
                {
                    "a": "Schulbibliothek Auf dem S\u00e4er"
                },
                {
                    "4": "a"
                }
            ],
            [
                {
                    "a": "N\u00fcrtingen Schulbibl."
                },
                {
                    "4": "c"
                }
            ]
        ],
        "029A": [
            [
                {
                    "a": "Schulbibliothek Fritz-Ruoff- und Albert-Sch\u00e4ffle-Schule N\u00fcrtingen"
                }
            ]
        ],
        "032P": [
            [
                {
                    "a": "Albert-Sch\u00e4ffle-Str. 7"
                },
                {
                    "b": "N\u00fcrtingen"
                },
                {
                    "d": "DE"
                },
                {
                    "e": "72622"
                },
                {
                    "f": "Baden-W\u00fcrttemberg"
                },
                {
                    "i": "Mo-Do 9.15-14.00, Fr 9.15-13.00"
                },
                {
                    "j": "in den Schulferien geschlossen"
                },
                {
                    "k": "9.35430"
                },
                {
                    "l": "48.62895"
                },
                {
                    "n": "08116049"
                },
                {
                    "o": "barrierefrei"
                },
                {
                    "p": "j"
                },
                {
                    "2": "S"
                }
            ]
        ],
        "035B": [
            [
                {
                    "a": "S"
                },
                {
                    "c": "j"
                },
                {
                    "d": "49"
                },
                {
                    "e": "7022"
                },
                {
                    "g": "93292-280"
                },
                {
                    "k": "bibliothek.frs@googlemail.com"
                }
            ]
        ],
        "035E": [
            [
                {
                    "a": "H"
                },
                {
                    "b": "s"
                },
                {
                    "f": "36"
                },
                {
                    "g": "03"
                },
                {
                    "h": "06"
                }
            ]
        ],
        "035I": [
            [
                {
                    "a": "BAW"
                },
                {
                    "b": "\u00dcLV"
                },
                {
                    "c": "SWB"
                },
                {
                    "e": "l"
                },
                {
                    "g": "V"
                }
            ]
        ],
        "035L": [
            [
                {
                    "a": "e"
                },
                {
                    "d": "bibliothek.frs@goolemail.com"
                }
            ]
        ]
    },
    "_id": "DE-2218",
    "seeAlso": "https://ld.zdb-services.de/resource/organisations/DE-2218",
    "sameAs": "https://ld.zdb-services.de/resource/organisations/DE-2218",
    "identifier": "DE-2218",
    "name": "Schulbibliothek Fritz-Ruoff- und Albert-Sch\u00e4ffle-Schule N\u00fcrtingen",
    "location": "N\u00fcrtingen",
    "type": [
        "Organization",
        "Library"
    ],
    "addressRegion": "BAW"
}