{
    "id": "https://sigel.staatsbibliothek-berlin.de/api/org/DE-2095.jsonld",
    "data": {
        "001A": [
            [
                [
                    "9006:14-03-14"
                ]
            ]
        ],
        "001B": [
            [
                [
                    "9006:28-01-16"
                ],
                {
                    "t": "16:25:45.000"
                }
            ]
        ],
        "001D": [
            [
                [
                    "9006:14-03-14"
                ]
            ]
        ],
        "001U": [
            [
                [
                    "utf8"
                ]
            ]
        ],
        "002@": [
            [
                [
                    "Tw"
                ]
            ]
        ],
        "003@": [
            [
                [
                    "1048481816"
                ]
            ]
        ],
        "008H": [
            [
                {
                    "b": "WD390"
                },
                {
                    "d": "2095"
                },
                {
                    "e": "DE-2095"
                }
            ]
        ],
        "009Q": [
            [
                {
                    "u": "http://www.georgenthal.de/scripts/angebote/3993?from=tourismus_freizeit&mainactive=5&subactive=10"
                },
                {
                    "z": "A"
                }
            ]
        ],
        "029@": [
            [
                {
                    "a": "Georgenthal StB"
                },
                {
                    "4": "c"
                }
            ]
        ],
        "029A": [
            [
                {
                    "a": "Gemeindebibliothek Georgenthal"
                }
            ]
        ],
        "032P": [
            [
                {
                    "a": "Bahnhofstr. 8"
                },
                {
                    "b": "Georgenthal"
                },
                {
                    "d": "DE"
                },
                {
                    "e": "99887"
                },
                {
                    "f": "Th\u00fcringen"
                },
                {
                    "i": "Mo 9.00-14.00, Di-Fr 9.00-18.00, Sa 9.00-12.00(Apr.-Okt.)"
                },
                {
                    "j": "Bibliothek u. Touristeninfo werden gemeinsam betreut"
                },
                {
                    "k": "10.66014"
                },
                {
                    "l": "50.83141"
                },
                {
                    "n": "16067025"
                },
                {
                    "o": "barrierefrei"
                },
                {
                    "p": "j"
                },
                {
                    "2": "S"
                }
            ]
        ],
        "035B": [
            [
                {
                    "a": "S"
                },
                {
                    "c": "j"
                },
                {
                    "d": "49"
                },
                {
                    "e": "36253"
                },
                {
                    "f": "46 97 55"
                },
                {
                    "g": "49"
                },
                {
                    "h": "36253"
                },
                {
                    "i": "46 98 14"
                },
                {
                    "k": "info@georgenthal.de"
                }
            ]
        ],
        "035E": [
            [
                {
                    "a": "H"
                },
                {
                    "b": "s"
                },
                {
                    "f": "33"
                },
                {
                    "g": "04"
                },
                {
                    "h": "04"
                }
            ]
        ],
        "035I": [
            [
                {
                    "a": "THU"
                },
                {
                    "c": "GBV"
                },
                {
                    "e": "l"
                }
            ]
        ],
        "035L": [
            [
                {
                    "a": "e"
                },
                {
                    "d": "info@georgenthal.de"
                }
            ],
            [
                {
                    "a": "f"
                },
                {
                    "d": "info@georgenthal.de"
                }
            ]
        ]
    },
    "_id": "DE-2095",
    "seeAlso": "https://ld.zdb-services.de/resource/organisations/DE-2095",
    "sameAs": "https://ld.zdb-services.de/resource/organisations/DE-2095",
    "identifier": "DE-2095",
    "name": "Gemeindebibliothek Georgenthal",
    "location": "Georgenthal",
    "type": [
        "Organization",
        "Library"
    ],
    "addressRegion": "THU"
}