{
    "id": "https://sigel.staatsbibliothek-berlin.de/api/org/DE-2355.jsonld",
    "data": {
        "001A": [
            [
                [
                    "9006:20-11-15"
                ]
            ]
        ],
        "001B": [
            [
                [
                    "9006:15-12-21"
                ],
                {
                    "t": "15:01:39.000"
                }
            ]
        ],
        "001D": [
            [
                [
                    "9006:20-11-15"
                ]
            ]
        ],
        "001U": [
            [
                [
                    "utf8"
                ]
            ]
        ],
        "002@": [
            [
                [
                    "Tw"
                ]
            ]
        ],
        "003@": [
            [
                [
                    "1079113533"
                ]
            ]
        ],
        "008H": [
            [
                {
                    "a": "358355-7"
                },
                {
                    "d": "2355"
                },
                {
                    "e": "DE-2355"
                }
            ]
        ],
        "009Q": [
            [
                {
                    "u": "http://www.archiv-jugendbewegung.de"
                },
                {
                    "z": "A"
                }
            ],
            [
                {
                    "u": "https://www.arcinsys.hessen.de"
                },
                {
                    "z": "B"
                }
            ]
        ],
        "029@": [
            [
                {
                    "a": "Witzenhausen AdJb"
                },
                {
                    "4": "c"
                }
            ]
        ],
        "029A": [
            [
                {
                    "a": "Archiv der deutschen Jugendbewegung, Bibliothek"
                }
            ]
        ],
        "032P": [
            [
                {
                    "a": "Burg Ludwigstein"
                },
                {
                    "b": "Witzenhausen"
                },
                {
                    "d": "DE"
                },
                {
                    "e": "37214"
                },
                {
                    "f": "Hessen"
                },
                {
                    "i": "Mo-Fr 8.30-11.45"
                },
                {
                    "j": "eine Verl\u00e4ngerung der \u00d6ffnungszeiten bis 16.30 Uhr ist nach Absprache m\u00f6glich"
                },
                {
                    "k": "9.90892"
                },
                {
                    "l": "51.32172"
                },
                {
                    "n": "06636016"
                },
                {
                    "p": "j"
                },
                {
                    "2": "S"
                }
            ]
        ],
        "035B": [
            [
                {
                    "a": "S"
                },
                {
                    "c": "j"
                },
                {
                    "d": "49"
                },
                {
                    "e": "5542"
                },
                {
                    "f": "50 17 20"
                },
                {
                    "g": "49"
                },
                {
                    "h": "5542"
                },
                {
                    "i": "50 17 23"
                },
                {
                    "k": "archiv@burgludwigstein.de"
                }
            ]
        ],
        "035E": [
            [
                {
                    "a": "H"
                },
                {
                    "b": "s"
                },
                {
                    "c": "0213"
                },
                {
                    "e": "HBV"
                },
                {
                    "f": "58"
                },
                {
                    "g": "02"
                },
                {
                    "h": "07"
                },
                {
                    "i": "P"
                },
                {
                    "l": "CC0"
                }
            ]
        ],
        "035G": [
            [
                {
                    "a": "Jugendbewegung"
                },
                {
                    "a": "Jugendkulturen"
                },
                {
                    "a": "Reformp\u00e4dagogik"
                },
                {
                    "a": "Lebensreform"
                },
                {
                    "a": "Jugendmusikbewegung"
                }
            ]
        ],
        "035I": [
            [
                {
                    "a": "HES"
                },
                {
                    "c": "HeBIS"
                },
                {
                    "e": "n"
                }
            ]
        ]
    },
    "_id": "DE-2355",
    "seeAlso": "https://ld.zdb-services.de/resource/organisations/DE-2355",
    "sameAs": "https://ld.zdb-services.de/resource/organisations/DE-2355",
    "identifier": "DE-2355",
    "name": "Archiv der deutschen Jugendbewegung, Bibliothek",
    "location": "Witzenhausen",
    "type": [
        "Organization",
        "Archive"
    ],
    "addressRegion": "HES"
}