{
    "id": "https://sigel.staatsbibliothek-berlin.de/api/org/DE-30-121.jsonld",
    "data": {
        "001A": [
            [
                [
                    "9006:11-07-00"
                ]
            ]
        ],
        "001B": [
            [
                [
                    "9006:29-11-19"
                ],
                {
                    "t": "15:15:20.000"
                }
            ]
        ],
        "001D": [
            [
                [
                    "9999:23-03-05"
                ]
            ]
        ],
        "001U": [
            [
                [
                    "utf8"
                ]
            ]
        ],
        "002@": [
            [
                [
                    "Tw"
                ]
            ]
        ],
        "003@": [
            [
                [
                    "020591004"
                ]
            ]
        ],
        "008H": [
            [
                {
                    "d": "30/121"
                },
                {
                    "e": "DE-30-121"
                }
            ]
        ],
        "029A": [
            [
                {
                    "a": "fr\u00fcher: Frankfurt/Main; Institut f\u00fcr Arbeits-, Wirtschafts- und Zivilrecht, Abteilung Bankrecht und Verkehrsrecht, Bibliothek"
                }
            ]
        ],
        "035E": [
            [
                {
                    "a": "I"
                },
                {
                    "k": "F 120b"
                }
            ]
        ],
        "047A": [
            [
                {
                    "a": "Ung\u00fcltig; Einrichtung wurde aufgel\u00f6st"
                }
            ]
        ]
    },
    "_id": "DE-30-121",
    "seeAlso": "https://ld.zdb-services.de/resource/organisations/DE-30-121",
    "sameAs": "https://ld.zdb-services.de/resource/organisations/DE-30-121",
    "identifier": "DE-30-121",
    "name": "fr\u00fcher: Frankfurt/Main; Institut f\u00fcr Arbeits-, Wirtschafts- und Zivilrecht, Abteilung Bankrecht und Verkehrsrecht, Bibliothek"
}