{
    "id": "https://sigel.staatsbibliothek-berlin.de/api/org/DE-5-66.jsonld",
    "data": {
        "001A": [
            [
                [
                    "9006:18-11-99"
                ]
            ]
        ],
        "001B": [
            [
                [
                    "9006:04-08-16"
                ],
                {
                    "t": "13:55:24.000"
                }
            ]
        ],
        "001D": [
            [
                [
                    "9999:23-03-05"
                ]
            ]
        ],
        "001U": [
            [
                [
                    "utf8"
                ]
            ]
        ],
        "002@": [
            [
                [
                    "Tw"
                ]
            ]
        ],
        "003@": [
            [
                [
                    "009012559"
                ]
            ]
        ],
        "008H": [
            [
                {
                    "d": "5/66"
                },
                {
                    "e": "DE-5-66"
                }
            ]
        ],
        "029A": [
            [
                {
                    "a": "fr\u00fcher: Bonn; Institut f\u00fcr Nutzpflanzenwissenschaften und Ressourcenschutz (INRES) / \u00d6kologie der Kulturlandschaft und Naturschutz, Tier\u00f6kologie, Bibliothek"
                }
            ]
        ],
        "035E": [
            [
                {
                    "a": "I"
                },
                {
                    "k": "Bo 66"
                }
            ]
        ],
        "047A": [
            [
                {
                    "a": "Ung\u00fcltig; Einrichtung wurde aufgel\u00f6st"
                }
            ]
        ]
    },
    "_id": "DE-5-66",
    "seeAlso": "https://ld.zdb-services.de/resource/organisations/DE-5-66",
    "sameAs": "https://ld.zdb-services.de/resource/organisations/DE-5-66",
    "identifier": "DE-5-66",
    "name": "fr\u00fcher: Bonn; Institut f\u00fcr Nutzpflanzenwissenschaften und Ressourcenschutz (INRES) / \u00d6kologie der Kulturlandschaft und Naturschutz, Tier\u00f6kologie, Bibliothek"
}