{
    "id": "https://sigel.staatsbibliothek-berlin.de/api/org/DE-986.jsonld",
    "data": {
        "001A": [
            [
                [
                    "9006:11-07-00"
                ]
            ]
        ],
        "001B": [
            [
                [
                    "9006:17-02-16"
                ],
                {
                    "t": "14:14:08.000"
                }
            ]
        ],
        "001D": [
            [
                [
                    "9999:23-03-05"
                ]
            ]
        ],
        "001U": [
            [
                [
                    "utf8"
                ]
            ]
        ],
        "002@": [
            [
                [
                    "Tw"
                ]
            ]
        ],
        "003@": [
            [
                [
                    "020587422"
                ]
            ]
        ],
        "008H": [
            [
                {
                    "b": "LD431"
                },
                {
                    "d": "986"
                },
                {
                    "e": "DE-986"
                }
            ]
        ],
        "009Q": [
            [
                {
                    "u": "http://www.filderstadt.de"
                },
                {
                    "z": "A"
                }
            ]
        ],
        "029@": [
            [
                {
                    "a": "Filderstadt StB"
                },
                {
                    "4": "c"
                }
            ]
        ],
        "029A": [
            [
                {
                    "a": "Stadtbibliothek Filderstadt, Zentralbibliothek"
                }
            ]
        ],
        "032P": [
            [
                {
                    "a": "Volmarstra\u00dfe 16"
                },
                {
                    "b": "Filderstadt"
                },
                {
                    "d": "DE"
                },
                {
                    "e": "70794"
                },
                {
                    "f": "Baden-W\u00fcrttemberg"
                },
                {
                    "i": "Di-Mi 10.00-14.00 und 15.00-19.00, Do-Fr 15.00-19.00, Sa 10.00-14.00"
                },
                {
                    "k": "9.21807"
                },
                {
                    "l": "48.67784"
                },
                {
                    "n": "08116077"
                },
                {
                    "p": "j"
                },
                {
                    "2": "S"
                }
            ]
        ],
        "035B": [
            [
                {
                    "a": "S"
                },
                {
                    "c": "j"
                },
                {
                    "d": "49"
                },
                {
                    "e": "711"
                },
                {
                    "f": "70 03-450"
                },
                {
                    "k": "bibliothek@filderstadt.de"
                }
            ]
        ],
        "035E": [
            [
                {
                    "a": "H"
                },
                {
                    "b": "s"
                },
                {
                    "f": "33"
                },
                {
                    "g": "04"
                },
                {
                    "h": "07"
                }
            ]
        ],
        "035I": [
            [
                {
                    "a": "BAW"
                },
                {
                    "b": "\u00dcLV"
                },
                {
                    "e": "l"
                },
                {
                    "g": "V"
                }
            ]
        ]
    },
    "_id": "DE-986",
    "seeAlso": "https://ld.zdb-services.de/resource/organisations/DE-986",
    "sameAs": "https://ld.zdb-services.de/resource/organisations/DE-986",
    "identifier": "DE-986",
    "name": "Stadtbibliothek Filderstadt, Zentralbibliothek",
    "location": "Filderstadt",
    "type": [
        "Organization",
        "Library"
    ],
    "addressRegion": "BAW"
}