{
    "id": "https://sigel.staatsbibliothek-berlin.de/api/org/DE-Hv8.jsonld",
    "data": {
        "001A": [
            [
                [
                    "9006:11-07-00"
                ]
            ]
        ],
        "001B": [
            [
                [
                    "9006:23-05-18"
                ],
                {
                    "t": "16:09:01.000"
                }
            ]
        ],
        "001D": [
            [
                [
                    "9999:23-03-05"
                ]
            ]
        ],
        "001U": [
            [
                [
                    "utf8"
                ]
            ]
        ],
        "002@": [
            [
                [
                    "Tw"
                ]
            ]
        ],
        "003@": [
            [
                [
                    "020592817"
                ]
            ]
        ],
        "008H": [
            [
                {
                    "b": "CU465"
                },
                {
                    "d": "Hv 8"
                },
                {
                    "e": "DE-Hv8"
                }
            ]
        ],
        "009Q": [
            [
                {
                    "u": "http://www.conti-online.de"
                },
                {
                    "z": "A"
                }
            ]
        ],
        "029@": [
            [
                {
                    "a": "Hannover Continental AG"
                },
                {
                    "4": "c"
                }
            ]
        ],
        "029A": [
            [
                {
                    "a": "Continental AG, Chemical Technical Information Center (CTIC)"
                }
            ]
        ],
        "032P": [
            [
                {
                    "a": "J\u00e4dekamp 30"
                },
                {
                    "b": "Hannover"
                },
                {
                    "d": "DE"
                },
                {
                    "e": "30419"
                },
                {
                    "f": "Niedersachsen"
                },
                {
                    "i": "nicht \u00f6ffentlich zug\u00e4nglich"
                },
                {
                    "k": "9.63881"
                },
                {
                    "l": "52.41765"
                },
                {
                    "n": "03241001"
                },
                {
                    "p": "j"
                },
                {
                    "2": "S"
                }
            ],
            [
                {
                    "b": "Hannover"
                },
                {
                    "d": "DE"
                },
                {
                    "e": "30001"
                },
                {
                    "f": "Niedersachsen"
                },
                {
                    "g": "1 69"
                },
                {
                    "p": "j"
                },
                {
                    "2": "P"
                }
            ]
        ],
        "035B": [
            [
                {
                    "a": "S"
                },
                {
                    "c": "j"
                },
                {
                    "d": "49"
                },
                {
                    "e": "511"
                },
                {
                    "f": "9 76-3720"
                },
                {
                    "g": "49"
                },
                {
                    "h": "511"
                },
                {
                    "i": "9 76-3840"
                }
            ]
        ],
        "035E": [
            [
                {
                    "a": "H"
                },
                {
                    "b": "s"
                },
                {
                    "f": "81"
                },
                {
                    "g": "08"
                },
                {
                    "h": "06"
                }
            ]
        ],
        "035G": [
            [
                {
                    "a": "Kautschuk"
                },
                {
                    "a": "Kautschuktechnologie"
                },
                {
                    "a": "Reifen"
                }
            ]
        ],
        "035I": [
            [
                {
                    "a": "NIE"
                },
                {
                    "e": "n"
                }
            ]
        ]
    },
    "_id": "DE-Hv8",
    "seeAlso": "https://ld.zdb-services.de/resource/organisations/DE-Hv8",
    "sameAs": "https://ld.zdb-services.de/resource/organisations/DE-Hv8",
    "identifier": "DE-Hv8",
    "name": "Continental AG, Chemical Technical Information Center (CTIC)",
    "location": "Hannover",
    "type": [
        "Organization",
        "Library"
    ],
    "addressRegion": "NIE"
}