{
    "id": "https://sigel.staatsbibliothek-berlin.de/api/org/DE-MUS-173811.jsonld",
    "data": {
        "001A": [
            [
                [
                    "9006:06-01-12"
                ]
            ]
        ],
        "001B": [
            [
                [
                    "9006:12-10-20"
                ],
                {
                    "t": "08:49:42.000"
                }
            ]
        ],
        "001D": [
            [
                [
                    "9006:06-01-12"
                ]
            ]
        ],
        "001U": [
            [
                [
                    "utf8"
                ]
            ]
        ],
        "002@": [
            [
                [
                    "Tw"
                ]
            ]
        ],
        "003@": [
            [
                [
                    "1018562826"
                ]
            ]
        ],
        "008H": [
            [
                {
                    "e": "DE-MUS-173811"
                }
            ]
        ],
        "009Q": [
            [
                {
                    "u": "http://www.uni-muenster.de/Bibelmuseum/"
                },
                {
                    "z": "A"
                }
            ],
            [
                {
                    "u": "http://www.museen-in-deutschland.de/singleview.php?muges=173811"
                },
                {
                    "x": "Weitere Informationen"
                },
                {
                    "z": "W"
                }
            ]
        ],
        "029A": [
            [
                {
                    "a": "Bibelmuseum"
                }
            ]
        ],
        "032P": [
            [
                {
                    "a": "Pferdegasse 1"
                },
                {
                    "b": "M\u00fcnster"
                },
                {
                    "d": "DE"
                },
                {
                    "e": "48143"
                },
                {
                    "f": "Nordrhein-Westfalen"
                },
                {
                    "k": "7.62349"
                },
                {
                    "l": "51.96124"
                },
                {
                    "p": "j"
                },
                {
                    "2": "S"
                }
            ]
        ],
        "035B": [
            [
                {
                    "a": "S"
                },
                {
                    "c": "j"
                },
                {
                    "d": "49"
                },
                {
                    "e": "251"
                },
                {
                    "f": "83 22-580"
                },
                {
                    "k": "bibelmuseum@uni-muenster.de"
                }
            ]
        ],
        "035E": [
            [
                {
                    "a": "H"
                },
                {
                    "b": "s"
                },
                {
                    "f": "86"
                }
            ]
        ],
        "035I": [
            [
                {
                    "d": "Kalliope"
                }
            ]
        ]
    },
    "_id": "DE-MUS-173811",
    "seeAlso": "https://ld.zdb-services.de/resource/organisations/DE-MUS-173811",
    "sameAs": "https://ld.zdb-services.de/resource/organisations/DE-MUS-173811",
    "identifier": "DE-MUS-173811",
    "name": "Bibelmuseum",
    "location": "M\u00fcnster",
    "type": [
        "Organization",
        "Museum"
    ]
}