{
    "id": "https://sigel.staatsbibliothek-berlin.de/api/org/DE-M359.jsonld",
    "data": {
        "001A": [
            [
                [
                    "9006:11-07-00"
                ]
            ]
        ],
        "001B": [
            [
                [
                    "9006:27-02-18"
                ],
                {
                    "t": "14:16:39.000"
                }
            ]
        ],
        "001D": [
            [
                [
                    "9999:23-03-05"
                ]
            ]
        ],
        "001U": [
            [
                [
                    "utf8"
                ]
            ]
        ],
        "002@": [
            [
                [
                    "Tw"
                ]
            ]
        ],
        "003@": [
            [
                [
                    "020596111"
                ]
            ]
        ],
        "008H": [
            [
                {
                    "a": "808359-9"
                },
                {
                    "b": "CT205"
                },
                {
                    "d": "M 359"
                },
                {
                    "e": "DE-M359"
                },
                {
                    "f": "MPIPP"
                }
            ]
        ],
        "009Q": [
            [
                {
                    "u": "http://www.ipp.mpg.de/infodok"
                },
                {
                    "z": "A"
                }
            ]
        ],
        "029@": [
            [
                {
                    "a": "Garching MPI Plasmaphysik"
                },
                {
                    "4": "c"
                }
            ]
        ],
        "029A": [
            [
                {
                    "a": "Max-Planck-Institut f\u00fcr Plasmaphysik, Bibliothek"
                }
            ]
        ],
        "032P": [
            [
                {
                    "a": "Boltzmannstr. 2"
                },
                {
                    "b": "Garching bei M\u00fcnchen"
                },
                {
                    "d": "DE"
                },
                {
                    "e": "85748"
                },
                {
                    "f": "Bayern"
                },
                {
                    "i": "Mo-Fr 8.00-19.00"
                },
                {
                    "j": "nicht \u00f6ffentlich zug\u00e4nglich"
                },
                {
                    "k": "11.67320"
                },
                {
                    "l": "48.26302"
                },
                {
                    "n": "09184119"
                },
                {
                    "p": "j"
                },
                {
                    "2": "S"
                }
            ]
        ],
        "035B": [
            [
                {
                    "a": "S"
                },
                {
                    "c": "j"
                },
                {
                    "d": "49"
                },
                {
                    "e": "89"
                },
                {
                    "f": "32 99-2182"
                },
                {
                    "g": "49"
                },
                {
                    "h": "89"
                },
                {
                    "i": "32 99-1181"
                },
                {
                    "k": "bibl@ipp.mpg.de"
                }
            ]
        ],
        "035E": [
            [
                {
                    "a": "H"
                },
                {
                    "b": "s"
                },
                {
                    "c": "0148"
                },
                {
                    "d": "MPG"
                },
                {
                    "f": "81"
                },
                {
                    "g": "08"
                },
                {
                    "h": "08"
                },
                {
                    "l": "CC0"
                }
            ]
        ],
        "035G": [
            [
                {
                    "a": "Plasmaphysik"
                },
                {
                    "a": "Kernfusion"
                }
            ]
        ],
        "035I": [
            [
                {
                    "a": "BAY"
                },
                {
                    "e": "n"
                }
            ]
        ]
    },
    "_id": "DE-M359",
    "seeAlso": "https://ld.zdb-services.de/resource/organisations/DE-M359",
    "sameAs": "https://ld.zdb-services.de/resource/organisations/DE-M359",
    "identifier": "DE-M359",
    "name": "Max-Planck-Institut f\u00fcr Plasmaphysik, Bibliothek",
    "location": "Garching bei M\u00fcnchen",
    "type": [
        "Organization",
        "Library"
    ],
    "addressRegion": "BAY"
}