{
    "id": "https://sigel.staatsbibliothek-berlin.de/api/org/DE-Rtb1.jsonld",
    "data": {
        "001A": [
            [
                [
                    "9006:13-07-06"
                ]
            ]
        ],
        "001B": [
            [
                [
                    "9006:17-10-16"
                ],
                {
                    "t": "15:51:01.000"
                }
            ]
        ],
        "001D": [
            [
                [
                    "9006:13-07-06"
                ]
            ]
        ],
        "001U": [
            [
                [
                    "utf8"
                ]
            ]
        ],
        "002@": [
            [
                [
                    "Tw"
                ]
            ]
        ],
        "003@": [
            [
                [
                    "980496136"
                ]
            ]
        ],
        "008H": [
            [
                {
                    "a": "838015-6"
                },
                {
                    "d": "Rtb 1"
                },
                {
                    "e": "DE-Rtb1"
                }
            ]
        ],
        "009Q": [
            [
                {
                    "u": "http://www.rottenburg-laaber.de/"
                },
                {
                    "z": "A"
                }
            ]
        ],
        "029@": [
            [
                {
                    "a": "Rottenburg/Laaber Stadtarchiv"
                },
                {
                    "4": "c"
                }
            ]
        ],
        "029A": [
            [
                {
                    "a": "Stadtarchiv Rottenburg a.d.Laaber"
                }
            ]
        ],
        "032P": [
            [
                {
                    "a": "Neufahrner Str. 1"
                },
                {
                    "b": "Rottenburg/Laaber"
                },
                {
                    "d": "DE"
                },
                {
                    "e": "84056"
                },
                {
                    "f": "Bayern"
                },
                {
                    "k": "12.02821"
                },
                {
                    "l": "48.70251"
                },
                {
                    "n": "09274176"
                },
                {
                    "p": "j"
                },
                {
                    "2": "S"
                }
            ]
        ],
        "035B": [
            [
                {
                    "a": "S"
                },
                {
                    "c": "j"
                },
                {
                    "d": "49"
                },
                {
                    "e": "8781"
                },
                {
                    "f": "2 06-0"
                },
                {
                    "g": "49"
                },
                {
                    "h": "8781"
                },
                {
                    "i": "2 06-690"
                },
                {
                    "k": "mail@rottenburg-laaber.de"
                }
            ]
        ],
        "035E": [
            [
                {
                    "a": "H"
                },
                {
                    "b": "s"
                },
                {
                    "c": "0167"
                },
                {
                    "f": "52"
                },
                {
                    "g": "04"
                },
                {
                    "h": "01"
                },
                {
                    "l": "CC0"
                }
            ]
        ],
        "035I": [
            [
                {
                    "a": "BAY"
                },
                {
                    "e": "n"
                }
            ]
        ]
    },
    "_id": "DE-Rtb1",
    "seeAlso": "https://ld.zdb-services.de/resource/organisations/DE-Rtb1",
    "sameAs": "https://ld.zdb-services.de/resource/organisations/DE-Rtb1",
    "identifier": "DE-Rtb1",
    "name": "Stadtarchiv Rottenburg a.d.Laaber",
    "location": "Rottenburg/Laaber",
    "type": [
        "Organization",
        "Archive"
    ],
    "addressRegion": "BAY"
}